{
    "en_US": {
        "CoinEx大使_eab5": "CoinEx大使推广活动规则及特别约定",
        "取消": "取消",
        "尚未勾选同意协议": "尚未勾选同意协议",
        "我已阅读并同意上_aa3e": "我已阅读并同意上述协议，承诺完全自行承担上述风险带来的责任和损失",
        "确定": "确定",
        "7×24小时客服_125e@DEPRECATED@": "7×24小时 专家支持"
    },
    "ja_JP": {
        "CoinEx大使_eab5": "CoinEx大使推广活动规则及特别约定",
        "取消": "取消",
        "尚未勾选同意协议": "尚未勾选同意协议",
        "我已阅读并同意上_aa3e": "我已阅读并同意上述协议，承诺完全自行承担上述风险带来的责任和损失",
        "确定": "确定",
        "7×24小时客服_125e@DEPRECATED@": "7×24小时 专家支持"
    },
    "ko_KP": {
        "CoinEx大使_eab5": "CoinEx大使推广活动规则及特别约定",
        "取消": "取消",
        "尚未勾选同意协议": "尚未勾选同意协议",
        "我已阅读并同意上_aa3e": "我已阅读并同意上述协议，承诺完全自行承担上述风险带来的责任和损失",
        "确定": "确定",
        "7×24小时客服_125e@DEPRECATED@": "7×24小时 专家支持"
    },
    "zh_Hans_CN": {
        "CoinEx大使_eab5": "CoinEx大使推广活动规则及特别约定",
        "取消": "取消",
        "尚未勾选同意协议": "尚未勾选同意协议",
        "我已阅读并同意上_aa3e": "我已阅读并同意上述协议，承诺完全自行承担上述风险带来的责任和损失",
        "确定": "确定",
        "7×24小时客服_125e@DEPRECATED@": "7×24小时 专家支持"
    },
    "zh_Hant_HK": {
        "CoinEx大使_eab5": "CoinEx大使推廣活動規則及特別約定",
        "取消": "取消",
        "尚未勾选同意协议": "尚未勾選同意協議",
        "我已阅读并同意上_aa3e": "我已閱讀並同意上述協議，承諾完全自行承擔上述風險帶來的責任和損失",
        "确定": "確定",
        "7×24小时客服_125e@DEPRECATED@": "7×24小时 专家支持"
    }
}